pary/__init__.py
pary/data.py
pary-0.0.2.dist-info/METADATA
pary-0.0.2.dist-info/WHEEL
pary-0.0.2.dist-info/licenses/LICENSE
pary-0.0.2.dist-info/RECORD
